CHANGES.txt
CONTRIBUTORS.txt
README.rst
bootstrap.py
buildout.cfg
setup.py
docs/LICENSE.GPL
docs/LICENSE.txt
src/collective/__init__.py
src/collective.codemirror.egg-info/PKG-INFO
src/collective.codemirror.egg-info/SOURCES.txt
src/collective.codemirror.egg-info/dependency_links.txt
src/collective.codemirror.egg-info/entry_points.txt
src/collective.codemirror.egg-info/namespace_packages.txt
src/collective.codemirror.egg-info/not-zip-safe
src/collective.codemirror.egg-info/requires.txt
src/collective.codemirror.egg-info/top_level.txt
src/collective/codemirror/__init__.py
src/collective/codemirror/configure.zcml
src/collective/codemirror/ptEdit.zpt
src/collective/codemirror/pyScriptEdit.dtml
src/collective/codemirror/static/codemirror-compressed.js
src/collective/codemirror/static/convertTextAreas.js
src/collective/codemirror/static/lib/LICENSE.txt
src/collective/codemirror/static/lib/codemirror.css