Metadata-Version: 1.0
Name: collective.codemirror
Version: 0.2
Summary: Integrate codemirror with Zope.
Home-page: http://github.com/collective/collective.codemirror
Author: UNKNOWN
Author-email: UNKNOWN
License: gpl
Platform: UNKNOWN
Classifier: Programming Language :: Python
